vibetracer/__init__.py
vibetracer/analysis/__init__.py
vibetracer/analysis/analyzer.py
vibetracer/analysis/config.py
vibetracer/command/__init__.py
vibetracer/command/analyze.py
vibetracer/command/run.py
vibetracer/command/runalyze.py
vibetracer/command/runner.py
vibetracer/database/__init__.py
vibetracer/database/config.py
vibetracer/database/dumper.py
vibetracer/database/models.py
vibetracer/database/sqlite_db.py
vibetracer/llm/__init__.py
vibetracer/llm/config.py
vibetracer/llm/fixer.py
vibetracer/llm/lib.py
vibetracer/llm/prompt_template.py
vibetracer/trace/__init__.py
vibetracer/trace/tracer.py
vibetracer-0.1.3.dist-info/licenses/LICENSE
vibetracer-0.1.3.dist-info/METADATA
vibetracer-0.1.3.dist-info/WHEEL
vibetracer-0.1.3.dist-info/entry_points.txt
vibetracer-0.1.3.dist-info/top_level.txt
vibetracer-0.1.3.dist-info/RECORD
