Metadata-Version: 2.4
Name: vibetracer
Version: 0.1.3
Summary: Lightweight function‐call tracer with SQLite backend, built for vibe coders.
Home-page: https://github.com/szamani20/VibeTracer
Author: Soroush Zamani
Author-email: Soroush Zamani <szchem20@gmail.com>
License: MIT
Project-URL: Homepage, https://github.com/szamani20/VibeTracer
Classifier: Programming Language :: Python :: 3
Classifier: License :: OSI Approved :: MIT License
Classifier: Operating System :: OS Independent
Requires-Python: >=3.8
License-File: LICENSE
Requires-Dist: sqlmodel>=0.0.24
Requires-Dist: SQLAlchemy>=2.0.41
Requires-Dist: matplotlib>=3.10.3
Requires-Dist: networkx>=3.5
Requires-Dist: openai>=1.93.0
Requires-Dist: anthropic>=0.55.0
Requires-Dist: google-genai>=1.23.0
Dynamic: author
Dynamic: home-page
Dynamic: license-file
Dynamic: requires-python
